<annotation>
	<folder>50-99</folder>
	<filename>50.png</filename>
	<path>/Users/pearse/Desktop/Cones/50-99/50.png</path>
	<source>
		<database>Unknown</database>
	</source>
	<size>
		<width>1280</width>
		<height>720</height>
		<depth>3</depth>
	</size>
	<segmented>0</segmented>
	<object>
		<name>yellow-cone</name>
		<pose>Unspecified</pose>
		<truncated>0</truncated>
		<difficult>0</difficult>
		<bndbox>
			<xmin>138</xmin>
			<ymin>423</ymin>
			<xmax>316</xmax>
			<ymax>650</ymax>
		</bndbox>
	</object>
	<object>
		<name>yellow-cone</name>
		<pose>Unspecified</pose>
		<truncated>0</truncated>
		<difficult>0</difficult>
		<bndbox>
			<xmin>186</xmin>
			<ymin>332</ymin>
			<xmax>259</xmax>
			<ymax>413</ymax>
		</bndbox>
	</object>
	<object>
		<name>blue-cone</name>
		<pose>Unspecified</pose>
		<truncated>0</truncated>
		<difficult>0</difficult>
		<bndbox>
			<xmin>664</xmin>
			<ymin>375</ymin>
			<xmax>704</xmax>
			<ymax>438</ymax>
		</bndbox>
	</object>
	<object>
		<name>blue-cone</name>
		<pose>Unspecified</pose>
		<truncated>0</truncated>
		<difficult>0</difficult>
		<bndbox>
			<xmin>954</xmin>
			<ymin>455</ymin>
			<xmax>1074</xmax>
			<ymax>593</ymax>
		</bndbox>
	</object>
</annotation>
